album_sender/__init__.py
album_sender-0.0.73.dist-info/LICENSE
album_sender-0.0.73.dist-info/METADATA
album_sender-0.0.73.dist-info/WHEEL
album_sender-0.0.73.dist-info/top_level.txt
album_sender-0.0.73.dist-info/RECORD
