Metadata-Version: 2.1
Name: album-sender
Version: 0.0.73
Summary: Telegram album sender.
Home-page: https://github.com/gaoyunzhi/telegram_album_sender
Author: Yunzhi Gao
Author-email: gaoyunzhi@gmail.com
License: UNKNOWN
Platform: UNKNOWN
Classifier: Programming Language :: Python :: 3
Classifier: License :: OSI Approved :: MIT License
Classifier: Operating System :: OS Independent
Requires-Python: >=3.0
License-File: LICENSE
Requires-Dist: cached-url
Requires-Dist: telegram-util
Requires-Dist: pic-cut
